.gitignore
MANIFEST.in
README.rst
setup.py
collective/__init__.py
collective.portlet.videoanysurfer.egg-info/PKG-INFO
collective.portlet.videoanysurfer.egg-info/SOURCES.txt
collective.portlet.videoanysurfer.egg-info/dependency_links.txt
collective.portlet.videoanysurfer.egg-info/entry_points.txt
collective.portlet.videoanysurfer.egg-info/namespace_packages.txt
collective.portlet.videoanysurfer.egg-info/not-zip-safe
collective.portlet.videoanysurfer.egg-info/requires.txt
collective.portlet.videoanysurfer.egg-info/top_level.txt
collective/portlet/__init__.py
collective/portlet/videoanysurfer/__init__.py
collective/portlet/videoanysurfer/configure.zcml
collective/portlet/videoanysurfer/transcription.pt
collective/portlet/videoanysurfer/videoportlet.pt
collective/portlet/videoanysurfer/videoportlet.py
collective/portlet/videoanysurfer/profiles/default/metadata.xml
collective/portlet/videoanysurfer/profiles/default/portlets.xml
collective/portlet/videoanysurfer/tests/__init__.py
collective/portlet/videoanysurfer/tests/base.py
collective/portlet/videoanysurfer/tests/test_portlet.py
docs/HISTORY.txt
docs/INSTALL.txt
docs/LICENSE.GPL
docs/LICENSE.txt