Metadata-Version: 1.0
Name: collective.portlet.videoanysurfer
Version: 1.0.3
Summary: Portlet to display video compliant with anysurfer
Home-page: https://github.com/collective/collective.portlet.videoanysurfer
Author: JeanMichel FRANCOIS aka toutpt
Author-email: toutpt@gmail.com
License: GPL
Keywords: plone video anysurfer
Platform: UNKNOWN
Classifier: Environment :: Web Environment
Classifier: License :: OSI Approved :: GNU General Public License (GPL)
Classifier: Operating System :: OS Independent
Classifier: Framework :: Plone
Classifier: Framework :: Plone :: 4.0
Classifier: Framework :: Plone :: 4.1
Classifier: Framework :: Plone :: 4.2
Classifier: Programming Language :: Python
